dillwave/__init__.py
dillwave/__main__.py
dillwave/dataset.py
dillwave/inference.py
dillwave/learner.py
dillwave/model.py
dillwave/params.py
dillwave/preprocess.py
dillwave-1.1.0.dist-info/LICENSE.txt
dillwave-1.1.0.dist-info/METADATA
dillwave-1.1.0.dist-info/WHEEL
dillwave-1.1.0.dist-info/top_level.txt
dillwave-1.1.0.dist-info/RECORD
