Metadata-Version: 2.1
Name: dillwave
Version: 1.1.0
Summary: dillwave
Home-page: https://dill.moe
Author: Cross Nastasi
Author-email: cross@dill.moe
License: Apache 2.0
Keywords: dillwave machine learning neural vocoder tts speech
Classifier: Development Status :: 4 - Beta
Classifier: Intended Audience :: Developers
Classifier: Intended Audience :: Education
Classifier: Intended Audience :: Science/Research
Classifier: License :: OSI Approved :: Apache Software License
Classifier: Programming Language :: Python :: 3.5
Classifier: Programming Language :: Python :: 3.6
Classifier: Programming Language :: Python :: 3.7
Classifier: Programming Language :: Python :: 3.8
Classifier: Topic :: Scientific/Engineering :: Mathematics
Classifier: Topic :: Software Development :: Libraries :: Python Modules
Classifier: Topic :: Software Development :: Libraries
License-File: LICENSE.txt
Requires-Dist: numpy
Requires-Dist: torch
Requires-Dist: torchaudio
Requires-Dist: tqdm
Requires-Dist: tensorboard
Requires-Dist: packaging
Requires-Dist: soundfile
